zpl/__init__.py
zpl/label.py
zpl/printer.py
zpl/trollface-large.png
zpl-0.1.12.dist-info/licenses/LICENSE
zpl-0.1.12.dist-info/METADATA
zpl-0.1.12.dist-info/WHEEL
zpl-0.1.12.dist-info/top_level.txt
zpl-0.1.12.dist-info/RECORD
